image_processing_userlo/__init__.py
image_processing_userlo/processing/__init__.py
image_processing_userlo/processing/combination.py
image_processing_userlo/processing/transformation.py
image_processing_userlo/utils/__init__.py
image_processing_userlo/utils/io.py
image_processing_userlo/utils/plot.py
image_processing_userlo-0.0.3.dist-info/METADATA
image_processing_userlo-0.0.3.dist-info/WHEEL
image_processing_userlo-0.0.3.dist-info/top_level.txt
image_processing_userlo-0.0.3.dist-info/RECORD
