Metadata-Version: 2.1
Name: image-processing-userlo
Version: 0.0.3
Summary: Meu primeiro pacotito
Home-page: https://github.com/loohxy/image-processing-package.git
Author: Lorena
Requires-Python: >=3.5
Requires-Dist: matplotlib
Requires-Dist: numpy
Requires-Dist: scikit-image>=0.16.1
